erqa/__init__.py
erqa/__main__.py
erqa/erqa.py
erqa-1.1.2.dist-info/LICENSE
erqa-1.1.2.dist-info/METADATA
erqa-1.1.2.dist-info/WHEEL
erqa-1.1.2.dist-info/top_level.txt
erqa-1.1.2.dist-info/RECORD
