Metadata-Version: 2.1
Name: erqa
Version: 1.1.2
Summary: A full-reference quality metric for analyzing restoration methods.
Home-page: https://github.com/msu-video-group/erqa
Author: Eugene Lyapustin
Author-email: evgeny.lyapustin@graphics.cs.msu.ru
License: UNKNOWN
Project-URL: Bug Tracker, https://github.com/msu-video-group/erqa/issues
Platform: UNKNOWN
Classifier: Programming Language :: Python :: 3
Classifier: License :: OSI Approved :: MIT License
Classifier: Operating System :: OS Independent
Requires-Python: >=3.6
License-File: LICENSE
Requires-Dist: numpy (>=1.14.3)
Requires-Dist: opencv-python (>=3.4.15)
